rez_pip/__init__.py
rez_pip/__main__.py
rez_pip/cli.py
rez_pip/compat.py
rez_pip/download.py
rez_pip/exceptions.py
rez_pip/install.py
rez_pip/patch.py
rez_pip/pip.py
rez_pip/rez.py
rez_pip/utils.py
rez_pip/data/__init__.py
rez_pip/data/pip.pyz
rez_pip/data/patches/__init__.py
rez_pip/data/patches/pyside6_6_0_0_win_dll_path.patch
rez_pip/data/patches/pyside6_6_1_0_win_dll_path.patch
rez_pip/data/patches/pyside6_6_2_4_win_dll_path.patch
rez_pip/data/patches/pyside6_6_3_0_win_dll_path.patch
rez_pip/data/patches/pyside6_6_7_3_win_dll_path.patch
rez_pip/data/patches/pyside6_6_8_1_win_dll_path.patch
rez_pip/plugins/PySide6.py
rez_pip/plugins/__init__.py
rez_pip/plugins/shiboken6.py
rez_pip-0.4.2.dist-info/METADATA
rez_pip-0.4.2.dist-info/WHEEL
rez_pip-0.4.2.dist-info/entry_points.txt
rez_pip-0.4.2.dist-info/licenses/LICENSE
rez_pip-0.4.2.dist-info/RECORD
