Metadata-Version: 2.4
Name: rez-pip
Version: 0.4.2
Summary: Modern rez-pip
Project-URL: Homepage, https://github.com/JeanChristopheMorinPerso/rez-pip
Project-URL: Tracker, https://github.com/JeanChristopheMorinPerso/rez-pip/issues
Project-URL: Documentation, https://rez-pip.readthedocs.io
Author-email: Jean-Christophe Morin <jean_christophe_morin@hotmail.com>
License:                                  Apache License
License-File: LICENSE
Classifier: Development Status :: 5 - Production/Stable
Classifier: License :: OSI Approved :: Apache Software License
Classifier: Natural Language :: English
Classifier: Operating System :: OS Independent
Classifier: Programming Language :: Python :: 3
Classifier: Programming Language :: Python :: 3.8
Classifier: Programming Language :: Python :: 3.9
Classifier: Programming Language :: Python :: 3.10
Classifier: Programming Language :: Python :: 3.11
Classifier: Programming Language :: Python :: 3.12
Classifier: Programming Language :: Python :: 3.13
Requires-Python: >=3.8
Requires-Dist: aiohttp
Requires-Dist: dataclasses-json
Requires-Dist: importlib-metadata>=4.6; python_version < '3.10'
Requires-Dist: installer>=0.7.0
Requires-Dist: packaging>=23.1
Requires-Dist: patch-ng==1.19.0
Requires-Dist: pluggy>=1.2
Requires-Dist: rez>=3.3.0
Requires-Dist: rich
